wasp_map/__init__.py
wasp_map/download.py
wasp_map/env.py
wasp_map/ldlib.py
wasp_map/map.py
wasp_map/wasp.py
wasp_map-0.3.5.dist-info/LICENSE
wasp_map-0.3.5.dist-info/METADATA
wasp_map-0.3.5.dist-info/WHEEL
wasp_map-0.3.5.dist-info/entry_points.txt
wasp_map-0.3.5.dist-info/top_level.txt
wasp_map-0.3.5.dist-info/RECORD
