Metadata-Version: 2.1
Name: wasp-map
Version: 0.3.5
Summary: Utilites for the mapping pipeline from WASP
Home-page: https://gitlab.com/aaylward/wasp_map
Author: Anthony Aylward
Author-email: aaylward@salk.edu
License: UNKNOWN
Platform: UNKNOWN
Classifier: Programming Language :: Python :: 3
Classifier: License :: OSI Approved :: MIT License
Classifier: Operating System :: OS Independent
License-File: LICENSE
Requires-Dist: gitpython
Requires-Dist: pyhg19
Requires-Dist: seqalign
